mxtoolbox/__init__.py
mxtoolbox/cli.py
mxtoolbox/client.py
mxtoolbox_client-0.1.0a0.dist-info/METADATA
mxtoolbox_client-0.1.0a0.dist-info/WHEEL
mxtoolbox_client-0.1.0a0.dist-info/entry_points.txt
mxtoolbox_client-0.1.0a0.dist-info/licenses/LICENSE
mxtoolbox_client-0.1.0a0.dist-info/RECORD
