Metadata-Version: 2.1
Name: mxtoolbox_client
Version: 0.1.0a0
Summary: A client for MX ToolBox API
Project-URL: Homepage, https://github.com/rpdeo/mxtoolbox-client
Project-URL: Bug Tracker, https://github.com/rpdeo/mxtoolbox-client/issues
Author: Rajesh P. Deo
License-File: LICENSE
Classifier: License :: OSI Approved :: MIT License
Classifier: Operating System :: OS Independent
Classifier: Programming Language :: Python :: 3
Requires-Python: >=3.7
